py_cyberiot_apollo/__init__.py
py_cyberiot_apollo/apollo.py
py_cyberiot_apollo-0.1.0.dist-info/METADATA
py_cyberiot_apollo-0.1.0.dist-info/WHEEL
py_cyberiot_apollo-0.1.0.dist-info/licenses/LICENSE
py_cyberiot_apollo-0.1.0.dist-info/RECORD
