Metadata-Version: 2.4
Name: py_cyberiot_apollo
Version: 0.1.0
Summary: cyberiot apollo device data collection
Project-URL: Homepage, https://github.com/cyberiot-apollo/py_cyberiot_apollo
Project-URL: Issues, https://github.com/cyberiot-apollo/py_cyberiot_apollo/issues
Author-email: cyberiot <service@eco-nest.net>
License: MIT
License-File: LICENSE
Classifier: License :: OSI Approved :: MIT License
Classifier: Operating System :: OS Independent
Classifier: Programming Language :: Python :: 3
Requires-Python: >=3.8
Requires-Dist: aiohttp>=3.9.3
